dtools/containers/__init__.py
dtools/containers/box.py
dtools/containers/functional_tuple.py
dtools/containers/immutable_list.py
dtools/containers/maybe.py
dtools/containers/py.typed
dtools/containers/xor.py
dtools_containers-1.0.0.dist-info/licenses/LICENSE
dtools_containers-1.0.0.dist-info/WHEEL
dtools_containers-1.0.0.dist-info/METADATA
dtools_containers-1.0.0.dist-info/RECORD
