Metadata-Version: 2.4
Name: dtools.containers
Version: 1.0.0
Summary: ### Developer Tools - Container-like data structures
Keywords: boxes,immutable_list,functional_tuple,maybe
Author-email: "Geoffrey R. Scheller" <geoffrey@scheller.com>
Requires-Python: >=3.12
Classifier: Development Status :: 5 - Production/Stable
Classifier: Framework :: Pytest
Classifier: Intended Audience :: Developers
Classifier: License :: OSI Approved :: Apache Software License
Classifier: Operating System :: OS Independent
Classifier: Programming Language :: Python :: 3.13
Classifier: Typing :: Typed
License-File: LICENSE
Requires-Dist: dtools.fp >=2.0.0, <2.1
Requires-Dist: dtools.iterables >=2.0.0, <2.1
Requires-Dist: pytest >=8.3.5 ; extra == "test"
Requires-Dist: dtools.queues >=2.0.0, <2.1 ; extra == "test"
Requires-Dist: dtools.splitends >=0.29.0, <0.30 ; extra == "test"
Project-URL: Changelog, https://github.com/grscheller/dtools-tuples/blob/main/CHANGELOG.md
Project-URL: Documentation, https://grscheller.github.io/dtools-namespace-projects/tuples
Project-URL: Homepage, https://github.com/grscheller/dtools-namespace-projects/blob/main/README.md
Project-URL: Source, https://github.com/grscheller/dtools-tuples
Provides-Extra: test
